<annotation verified="yes">
	<folder>ภาพมุมสูงเพิ่ม(2020)</folder>
	<filename>DJI_0286.JPG</filename>
	<path>/Volumes/Macintosh HD/SeniorProject/CarDetectProject/Data/ภาพรถมุมสูง/ภาพมุมสูงเพิ่ม(2020)/DJI_0286.JPG</path>
	<source>
		<database>Unknown</database>
	</source>
	<size>
		<width>4000</width>
		<height>3000</height>
		<depth>3</depth>
	</size>
	<segmented>0</segmented>
	<object>
		<name>car</name>
		<pose>Unspecified</pose>
		<truncated>0</truncated>
		<difficult>0</difficult>
		<bndbox>
			<xmin>1592</xmin>
			<ymin>533</ymin>
			<xmax>1781</xmax>
			<ymax>751</ymax>
		</bndbox>
	</object>
	<object>
		<name>car</name>
		<pose>Unspecified</pose>
		<truncated>0</truncated>
		<difficult>0</difficult>
		<bndbox>
			<xmin>1746</xmin>
			<ymin>1279</ymin>
			<xmax>1935</xmax>
			<ymax>1497</ymax>
		</bndbox>
	</object>
	<object>
		<name>car</name>
		<pose>Unspecified</pose>
		<truncated>0</truncated>
		<difficult>0</difficult>
		<bndbox>
			<xmin>1592</xmin>
			<ymin>1299</ymin>
			<xmax>1781</xmax>
			<ymax>1517</ymax>
		</bndbox>
	</object>
</annotation>
